[
  {
    "ITEM": "Big Mac",
    "CAL": "550",
    "PRICE": "$$$",
    "CATEGORY": "BURGERSANDWICH",
    "ID": "0"
  },
  {
    "ITEM": "Quarter Pounder with Cheese",
    "CAL": "510",
    "PRICE": "$$",
    "CATEGORY": "BURGERSANDWICH",
    "ID": "1"
  },
  {
    "ITEM": "Double Quarter Pounder with Cheese",
    "CAL": "720",
    "PRICE": "$$$",
    "CATEGORY": "BURGERSANDWICH",
    "ID": "2"
  },
  {
    "ITEM": "Quarter Pounder with Cheese Deluxe",
    "CAL": "620",
    "PRICE": "$$$",
    "CATEGORY": "BURGERSANDWICH",
    "ID": "3"
  },
  {
    "ITEM": "McDouble",
    "CAL": "390",
    "PRICE": "$$",
    "CATEGORY": "BURGERSANDWICH",
    "ID": "4"
  },
  {
    "ITEM": "Cheese Burger",
    "CAL": "300",
    "PRICE": "$",
    "CATEGORY": "BURGERSANDWICH",
    "ID": "5"
  },
  {
    "ITEM": "Burger",
    "CAL": "250",
    "PRICE": "$",
    "CATEGORY": "BURGERSANDWICH",
    "ID": "6"
  },
  {
    "ITEM": "Soda",
    "CAL": "290",
    "PRICE": "$$",
    "CATEGORY": "BEVERAGE",
    "ID": "7"
  },
  {
    "ITEM": "Bottled Water",
    "CAL": "0",
    "PRICE": "$",
    "CATEGORY": "BEVERAGE",
    "ID": "8"
  },
  {
    "ITEM": "Lemonade Slushie",
    "CAL": "350",
    "PRICE": "$$",
    "CATEGORY": "BEVERAGE",
    "ID": "9"
  },
  {
    "ITEM": "Coffee",
    "CAL": "210",
    "PRICE": "$",
    "CATEGORY": "BEVERAGE",
    "ID": "10"
  },
  {
    "ITEM": "McChicken",
    "CAL": "400",
    "PRICE": "$$",
    "CATEGORY": "CHICKENFISH",
    "ID": "11"
  },
  {
    "ITEM": "Chicken McNuggets",
    "CAL": "420",
    "PRICE": "$$$",
    "CATEGORY": "CHICKENFISH",
    "ID": "12"
  },
  {
    "ITEM": "Filet-O-Fish",
    "CAL": "380",
    "PRICE": "$$",
    "CATEGORY": "CHICKENFISH",
    "ID": "13"
  },
  {
    "ITEM": "Baked Apple Pie",
    "CAL": "240",
    "PRICE": "$",
    "CATEGORY": "DESSERTSHAKE",
    "ID": "14"
  },
  {
    "ITEM": "Chocolate Chip Cookie",
    "CAL": "170",
    "PRICE": "$",
    "CATEGORY": "DESSERTSHAKE",
    "ID": "15"
  },
  {
    "ITEM": "Milk Shake",
    "CAL": "840",
    "PRICE": "$$$",
    "CATEGORY": "DESSERTSHAKE",
    "ID": "16"
  },
  {
    "ITEM": "Ice-Cream Cone",
    "CAL": "200",
    "PRICE": "$",
    "CATEGORY": "DESSERTSHAKE",
    "ID": "17"
  },
  {
    "ITEM": "Hot Fudge Sundae",
    "CAL": "330",
    "PRICE": "$$",
    "CATEGORY": "DESSERTSHAKE",
    "ID": "18"
  },
  {
    "ITEM": "McFlurry",
    "CAL": "640",
    "PRICE": "$$$",
    "CATEGORY": "DESSERTSHAKE",
    "ID": "19"
  },
  {
    "ITEM": "Fries",
    "CAL": "490",
    "PRICE": "$$",
    "CATEGORY": "SNACKSIDE",
    "ID": "20"
  },
  {
    "ITEM": "Apple Slices",
    "CAL": "15",
    "PRICE": "$",
    "CATEGORY": "SNACKSIDE",
    "ID": "21"
  },
  {
    "ITEM": "Bacon, Egg & Cheese Biscuit",
    "CAL": "460",
    "PRICE": "$$",
    "CATEGORY": "BREAKFAST",
    "ID": "22"
  },
  {
    "ITEM": "Egg McMuffin",
    "CAL": "300",
    "PRICE": "$$",
    "CATEGORY": "BREAKFAST",
    "ID": "23"
  },
  {
    "ITEM": "Sausage Biscuit",
    "CAL": "460",
    "PRICE": "$$",
    "CATEGORY": "BREAKFAST",
    "ID": "24"
  },
  {
    "ITEM": "Hash Browns",
    "CAL": "140",
    "PRICE": "$",
    "CATEGORY": "BREAKFAST",
    "ID": "25"
  },
  {
    "ITEM": "Sausage Burrito",
    "CAL": "310",
    "PRICE": "$$",
    "CATEGORY": "BREAKFAST",
    "ID": "26"
  }
]
